csvs_convert-0.7.3.dist-info/METADATA
csvs_convert-0.7.3.dist-info/WHEEL
csvs_convert-0.7.3.dist-info/license_files/LICENSE
csvs_convert/__init__.py
csvs_convert/tests.py
csvs_convert/csvs_convert.cpython-311-darwin.so
csvs_convert-0.7.3.dist-info/RECORD
