Metadata-Version: 2.1
Name: csvs_convert
Version: 0.7.3
Requires-Dist: openpyxl; extra == 'dev'
Requires-Dist: pandas; extra == 'dev'
Requires-Dist: pyarrow; extra == 'dev'
Requires-Dist: sphynx; extra == 'dev'
Requires-Dist: furo==2022.4.7; extra == 'dev'
Requires-Dist: myst_parser; extra == 'dev'
Provides-Extra: dev
License-File: LICENSE
Summary: Convert your csvs fast
